Pack/ModC.py
Pack/__init__.py
ModCvs-2.0.dist-info/METADATA
ModCvs-2.0.dist-info/WHEEL
ModCvs-2.0.dist-info/top_level.txt
ModCvs-2.0.dist-info/RECORD
