Metadata-Version: 2.1
Name: ModCvs
Version: 2.0
Summary: yn nouvel vesyon de aplikasyon an ki bazel sou klas
Author: Samuel Ovide & Sivenson Bellamour
Requires-Python: >=3.8
